pylancelot-0.7.0.dist-info/METADATA
pylancelot-0.7.0.dist-info/WHEEL
lancelot/__init__.py
lancelot/lancelot.pypy37-pp73-i686-linux-gnu.so
pylancelot-0.7.0.dist-info/RECORD
