Metadata-Version: 2.1
Name: pylancelot
Version: 0.7.0
Classifier: Programming Language :: Rust
Classifier: Development Status :: 3 - Alpha
Classifier: License :: OSI Approved :: Apache Software License
Classifier: Natural Language :: English
Classifier: Operating System :: OS Independent
Classifier: Topic :: Security
Classifier: Topic :: Software Development :: Disassemblers
Requires-Dist: pefile
Home-Page: https://github.com/williballenthin/lancelot
Author: Willi Ballenthin <wilbal1087@gmail.com>
Author-email: Willi Ballenthin <wilbal1087@gmail.com>
Project-URL: Source Code, https://github.com/williballenthin/lancelot
